transpyjs/__init__.py
transpyjs/__main__.py
transpyjs/sub_dir/__init__.py
transpyjs/sub_dir/transpyjs.py
transpyjs-0.0.1.dist-info/METADATA
transpyjs-0.0.1.dist-info/WHEEL
transpyjs-0.0.1.dist-info/entry_points.txt
transpyjs-0.0.1.dist-info/top_level.txt
transpyjs-0.0.1.dist-info/RECORD
